psevdocompilerlib/__init__.py
psevdocompilerlib/lib.py
psevdocompilerlib-1.0.0.dist-info/LICENSE
psevdocompilerlib-1.0.0.dist-info/METADATA
psevdocompilerlib-1.0.0.dist-info/WHEEL
psevdocompilerlib-1.0.0.dist-info/top_level.txt
psevdocompilerlib-1.0.0.dist-info/RECORD
