Metadata-Version: 2.1
Name: psevdocompilerlib
Version: 1.0.0
Summary: Compile the Russian psevdocode!
Author-email: Arigadam <arigadam938@hotmail.com>
Classifier: Programming Language :: Python :: 3
Classifier: License :: OSI Approved :: MIT License
Classifier: Operating System :: OS Independent
Requires-Python: >=3.11
License-File: LICENSE
Requires-Dist: requests
